ndip_topaz_reduction/README.md
ndip_topaz_reduction/__init__.py
ndip_topaz_reduction/dist/ndip_topaz_reduction-0.1.0.tar.gz
ndip_topaz_reduction/galaxy_interface.py
ndip_topaz_reduction/pyproject.toml
ndip_topaz_reduction/utilities/__init__.py
ndip_topaz_reduction/utilities/data_processing.py
ndip_topaz_reduction/utilities/job_management.py
ndip_topaz_reduction-0.1.0.dist-info/METADATA
ndip_topaz_reduction-0.1.0.dist-info/WHEEL
ndip_topaz_reduction-0.1.0.dist-info/RECORD
