Metadata-Version: 2.1
Name: ndip-topaz-reduction
Version: 0.1.0
Summary: 
Author: DeLozier, Jenna
Author-email: delozierjk@ornl.gov
Requires-Python: >=3.11,<4.0
Classifier: Programming Language :: Python :: 3
Classifier: Programming Language :: Python :: 3.11
Classifier: Programming Language :: Python :: 3.12
